flag.py
artifact_lab_3_package_24ddbc49-0.4.0.dist-info/METADATA
artifact_lab_3_package_24ddbc49-0.4.0.dist-info/WHEEL
artifact_lab_3_package_24ddbc49-0.4.0.dist-info/entry_points.txt
artifact_lab_3_package_24ddbc49-0.4.0.dist-info/top_level.txt
artifact_lab_3_package_24ddbc49-0.4.0.dist-info/RECORD
