Metadata-Version: 2.1
Name: artifact_lab_3_package_24ddbc49
Version: 0.4.0
Summary: Leaking environment variables via HTTP requests. Used in Hacktricks GRTE class.
Author: Your Mum
Author-email: your_email@example.com
Classifier: Programming Language :: Python :: 3
Classifier: License :: OSI Approved :: MIT License
Classifier: Operating System :: OS Independent
Requires-Python: >=3.7
Requires-Dist: requests
